README
pytranslate.py
setup.py
pytranslate.egg-info/PKG-INFO
pytranslate.egg-info/SOURCES.txt
pytranslate.egg-info/dependency_links.txt
pytranslate.egg-info/top_level.txt