Metadata-Version: 1.0
Name: pytranslate
Version: 0.1.4
Summary: Google Translate wrapper for Python.
Home-page: http://stockrt.github.com
Author: Rogério Carvalho Schneider
Author-email: stockrt@gmail.com
License: GPLv3
Download-URL: http://stockrt.github.com
Keywords: google translate wrapper pytranslate
Platform: any
Classifier: Development Status :: 1 - Planning
Classifier: Environment :: Web Environment
Classifier: Intended Audience :: Information Technology
Classifier: License :: OSI Approved :: GNU General Public License (GPL)
Classifier: Natural Language :: English
Classifier: Operating System :: POSIX :: Linux
Classifier: Programming Language :: Python
Classifier: Topic :: Utilities
